dcTrackClient/__init__.py
dctrackclient-1.5.1.dist-info/METADATA
dctrackclient-1.5.1.dist-info/WHEEL
dctrackclient-1.5.1.dist-info/RECORD
