Metadata-Version: 2.4
Name: dcTrackClient
Version: 1.5.1
Summary: Sunbird dcTrack API client in Python
Project-URL: Homepage, https://github.com/nicfv/dcTrackClient/
Project-URL: Bug Tracker, https://github.com/nicfv/dcTrackClient/pulls
Author-email: Nicolas Ventura <ventura@lbl.gov>
Classifier: Development Status :: 5 - Production/Stable
Classifier: Intended Audience :: Developers
Classifier: License :: OSI Approved :: BSD License
Classifier: Natural Language :: English
Classifier: Operating System :: OS Independent
Classifier: Programming Language :: Python :: 3
Requires-Python: >=3.7
Requires-Dist: requests
Requires-Dist: requests[socks]
